whatsapp_cloud_sdk/__init__.py
whatsapp_cloud_sdk/_base_api.py
whatsapp_cloud_sdk/bot.py
whatsapp_cloud_sdk/wamanager.py
whatsapp_cloud_sdk/_exceptions/__init__.py
whatsapp_cloud_sdk/_exceptions/http_error.py
whatsapp_cloud_sdk/_files/__init__.py
whatsapp_cloud_sdk/_files/contact.py
whatsapp_cloud_sdk/_files/file_object.py
whatsapp_cloud_sdk/_files/image.py
whatsapp_cloud_sdk/_files/location.py
whatsapp_cloud_sdk/_files/message.py
whatsapp_cloud_sdk/_files/reaction.py
whatsapp_cloud_sdk/_files/sticker.py
whatsapp_cloud_sdk/_formaters/__init__.py
whatsapp_cloud_sdk/_formaters/message_formatter.py
whatsapp_cloud_sdk/_utils/__init__.py
whatsapp_cloud_sdk/_utils/json_serializer.py
whatsapp_cloud_sdk/_utils/types.py
whatsapp_cloud_sdk/_validators/__init__.py
whatsapp_cloud_sdk/_validators/messages.py
whatsapp_cloud_sdk/_validators/server.py
whatsapp_cloud_sdk-1.0.2.dist-info/LICENSE
whatsapp_cloud_sdk-1.0.2.dist-info/METADATA
whatsapp_cloud_sdk-1.0.2.dist-info/WHEEL
whatsapp_cloud_sdk-1.0.2.dist-info/top_level.txt
whatsapp_cloud_sdk-1.0.2.dist-info/RECORD
