Metadata-Version: 2.1
Name: whatsapp-cloud-sdk
Version: 1.0.2
Summary: A library(SDK) that provides a Python interface to the Whatsapp Cloud API
Author-email: Akpojiyovwi Tega <beniyoke@gmail.com>
Maintainer-email: Akpojiyovwi Tega <beniyoke@gmail.com>
License: GNU GENERAL PUBLIC LICENSE
Project-URL: Homepage, https://github.com/t-ega/Whatsapp-Python-SDK/
Project-URL: Repository, https://github.com/t-ega/Whatsapp-Python-SDK/
Keywords: whatsapp,whatsapp-bot,sdk-python, whatsapp-api
Classifier: Development Status :: 3 - Alpha
Classifier: Intended Audience :: Developers
Classifier: Topic :: Software Development :: Libraries
Classifier: License :: OSI Approved :: MIT License
Classifier: Programming Language :: Python :: 3.6
Classifier: Programming Language :: Python :: 3.7
Classifier: Programming Language :: Python :: 3.8
Classifier: Programming Language :: Python :: 3.9
Requires-Python: >=3.6
License-File: LICENSE
Requires-Dist: annotated-types ==0.5.0
Requires-Dist: anyio ==3.7.1
Requires-Dist: astroid ==3.0.0
Requires-Dist: certifi ==2023.7.22
Requires-Dist: charset-normalizer ==3.3.0
Requires-Dist: click ==8.1.7
Requires-Dist: colorama ==0.4.6
Requires-Dist: dill ==0.3.7
Requires-Dist: exceptiongroup ==1.1.3
Requires-Dist: fastapi ==0.103.2
Requires-Dist: h11 ==0.14.0
Requires-Dist: idna ==3.4
Requires-Dist: isort ==5.12.0
Requires-Dist: mccabe ==0.7.0
Requires-Dist: platformdirs ==3.11.0
Requires-Dist: pydantic ==2.4.2
Requires-Dist: pydantic-core ==2.10.1
Requires-Dist: pylint ==3.0.1
Requires-Dist: python-dotenv ==1.0.0
Requires-Dist: requests ==2.31.0
Requires-Dist: sniffio ==1.3.0
Requires-Dist: starlette ==0.27.0
Requires-Dist: tomli ==2.0.1
Requires-Dist: tomlkit ==0.12.1
Requires-Dist: typing-extensions ==4.8.0
Requires-Dist: urllib3 ==2.0.6
Requires-Dist: uvicorn ==0.23.2
